flytrap/__init__.py
flytrap/config.py
flytrap_flask-1.0.1.dist-info/METADATA
flytrap_flask-1.0.1.dist-info/WHEEL
flytrap_flask-1.0.1.dist-info/top_level.txt
flytrap_flask-1.0.1.dist-info/RECORD
