Metadata-Version: 2.1
Name: flytrap_flask
Version: 1.0.1
Home-page: https://github.com/getflytrap/flytrap_flask
Project-URL: Homepage, https://getflytrap.github.io/
Requires-Python: >=3.6
Requires-Dist: Flask
Requires-Dist: requests
